ducktools/lazyimporter/__init__.py
ducktools/lazyimporter/__init__.pyi
ducktools/lazyimporter/capture.py
ducktools/lazyimporter/capture.pyi
ducktools/lazyimporter/py.typed
ducktools_lazyimporter-0.8.3.dist-info/licenses/LICENSE
ducktools_lazyimporter-0.8.3.dist-info/METADATA
ducktools_lazyimporter-0.8.3.dist-info/WHEEL
ducktools_lazyimporter-0.8.3.dist-info/top_level.txt
ducktools_lazyimporter-0.8.3.dist-info/RECORD
